Metadata-Version: 2.1
Name: odoo13-addon-stock-picking-batch-extended
Version: 13.0.1.3.0
Summary: Allows manage a lot of pickings in batch
Home-page: https://github.com/OCA/stock-logistics-workflow
Author: Camptocamp, Tecnativa, Odoo Community Association (OCA)
Author-email: support@odoo-community.org
License: AGPL-3
Platform: UNKNOWN
Classifier: Programming Language :: Python
Classifier: Framework :: Odoo
Classifier: License :: OSI Approved :: GNU Affero General Public License v3
Classifier: Development Status :: 6 - Mature
Requires-Python: >=3.5
Requires-Dist: odoo (<13.1dev,>=13.0a)
